[
    {
        "transactionName": "WebTourConnection",
        "rawStartTime": 1630746363933,
        "rawEndTime": 1630746364104
    },
    {
        "transactionName": "PressSignup",
        "rawStartTime": 1630746364137,
        "rawEndTime": 1630746364246
    },
    {
        "transactionName": "Signup",
        "rawStartTime": 1630746364279,
        "rawEndTime": 1630746364406
    },
    {
        "transactionName": "PressNext",
        "rawStartTime": 1630746364422,
        "rawEndTime": 1630746364610
    },
    {
        "transactionName": "02_GeneralTransaction",
        "rawStartTime": 1630746363918,
        "rawEndTime": 1630746364626
    }
]