[
    {
        "transactionName": "WebTourConnection",
        "rawStartTime": 1631463835567,
        "rawEndTime": 1631463835801
    },
    {
        "transactionName": "Login",
        "rawStartTime": 1631463835895,
        "rawEndTime": 1631463836189
    },
    {
        "transactionName": "Flights",
        "rawStartTime": 1631463836284,
        "rawEndTime": 1631463836520
    },
    {
        "transactionName": "SearchFlight",
        "rawStartTime": 1631463836597,
        "rawEndTime": 1631463836835
    },
    {
        "transactionName": "ChooseFlight",
        "rawStartTime": 1631463836930,
        "rawEndTime": 1631463837180
    },
    {
        "transactionName": "PaymentData",
        "rawStartTime": 1631463837243,
        "rawEndTime": 1631463837445
    },
    {
        "transactionName": "Itinerary",
        "rawStartTime": 1631463837523,
        "rawEndTime": 1631463837678
    },
    {
        "transactionName": "0404_BuyFlight",
        "rawStartTime": 1631463835505,
        "rawEndTime": 1631463837756
    }
]