[
    {
        "stepId": "STEP36",
        "stepName": "Url: WebTours",
        "infFile": "t1.inf",
        "time": 1630847660635
    },
    {
        "stepId": "STEP37",
        "stepName": "Submit Data: login.pl",
        "infFile": "t2.inf",
        "time": 1630847660946
    },
    {
        "stepId": "STEP38",
        "stepName": "Url: Search Flights Button",
        "infFile": "t3.inf",
        "time": 1630847661258
    },
    {
        "stepId": "STEP39",
        "stepName": "Submit Data: reservations.pl",
        "infFile": "t4.inf",
        "time": 1630847661549
    },
    {
        "stepId": "STEP40",
        "stepName": "Submit Data: reservations.pl_2",
        "infFile": "t5.inf",
        "time": 1630847661825
    }
]