[
    {
        "transactionName": "WebTourConnection",
        "rawStartTime": 1631460487264,
        "rawEndTime": 1631460487500
    },
    {
        "transactionName": "Login",
        "rawStartTime": 1631460487578,
        "rawEndTime": 1631460487798
    },
    {
        "transactionName": "Itinerary",
        "rawStartTime": 1631460487877,
        "rawEndTime": 1631460488130
    },
    {
        "transactionName": "delete_tickets",
        "rawStartTime": 1631460488227,
        "rawEndTime": 1631460488367
    },
    {
        "transactionName": "SignOff",
        "rawStartTime": 1631460488446,
        "rawEndTime": 1631460488621
    },
    {
        "transactionName": "05050_Delete",
        "rawStartTime": 1631460487216,
        "rawEndTime": 1631460488699
    }
]